sklearn2excel/__init__.py
sklearn2excel/core.py
sklearn2excel/helpers.py
sklearn2excel-0.1.1.dist-info/LICENSE
sklearn2excel-0.1.1.dist-info/WHEEL
sklearn2excel-0.1.1.dist-info/METADATA
sklearn2excel-0.1.1.dist-info/RECORD
