Metadata-Version: 2.1
Name: sklearn2excel
Version: 0.1.1
Summary: A Python package to facilitate Scikit-learn decision tree export to Excel.
Author-email: Torbjørn Wikestad <torbjorn.wikestad@gmail.com>
Classifier: License :: OSI Approved :: MIT License
Requires-Dist: XlsxWriter >=3.0, <4
Requires-Dist: scikit-learn >=1.0, <2
Project-URL: Home, https://github.com/tobisan5/sklearn2excel
